st_signedUrl_uploader/__init__.py
st_signedUrl_uploader/frontend/build/asset-manifest.json
st_signedUrl_uploader/frontend/build/bootstrap.min.css
st_signedUrl_uploader/frontend/build/index.html
st_signedUrl_uploader/frontend/build/static/js/main.dc852d56.js
st_signedUrl_uploader/frontend/build/static/js/main.dc852d56.js.LICENSE.txt
st_signedUrl_uploader/frontend/build/static/js/main.dc852d56.js.map
st_signedUrl_uploader_noz-1.3.2.dist-info/LICENSE
st_signedUrl_uploader_noz-1.3.2.dist-info/METADATA
st_signedUrl_uploader_noz-1.3.2.dist-info/WHEEL
st_signedUrl_uploader_noz-1.3.2.dist-info/top_level.txt
st_signedUrl_uploader_noz-1.3.2.dist-info/RECORD
