Metadata-Version: 2.1
Name: st-signedUrl-uploader-noz
Version: 1.3.2
Summary: Updated version of the Streamlit component that allows you to upload files to Google Cloud Storage via signed url
Home-page: 
Author: Meryam Assermouh, Seyedalireza Yaghoubi
Author-email: seyedalirezayaghobi@outlook.com
Requires-Python: >=3.7
License-File: LICENSE
Requires-Dist: streamlit >=0.63
Provides-Extra: devel
Requires-Dist: wheel ; extra == 'devel'
Requires-Dist: pytest ==7.4.0 ; extra == 'devel'
Requires-Dist: playwright ==1.39.0 ; extra == 'devel'
Requires-Dist: requests ==2.31.0 ; extra == 'devel'
Requires-Dist: pytest-playwright-snapshot ==1.0 ; extra == 'devel'
Requires-Dist: pytest-rerunfailures ==12.0 ; extra == 'devel'
